wav2clip/__init__.py
wav2clip/model/__init__.py
wav2clip/model/encoder.py
wav2clip/model/resnet.py
wav2clip/pre_training/__init__.py
wav2clip/pre_training/dataset.py
wav2clip/pre_training/loss.py
wav2clip/pre_training/model.py
wav2clip-0.1.0.dist-info/LICENSE.md
wav2clip-0.1.0.dist-info/METADATA
wav2clip-0.1.0.dist-info/WHEEL
wav2clip-0.1.0.dist-info/top_level.txt
wav2clip-0.1.0.dist-info/RECORD
