Metadata-Version: 2.1
Name: wav2clip
Version: 0.1.0
Summary: Wav2CLIP: Learning Robust Audio Representations From CLIP.
Home-page: https://github.com/descriptinc/lyrebird-wav2clip
Author: Ho-Hsiang Wu
Author-email: hohsiang@descript.com
License: MIT
Keywords: audio,representation,learning,music,sound,representation learning,wav2clip
Platform: UNKNOWN
Classifier: Intended Audience :: Developers
Classifier: Intended Audience :: Education
Classifier: Intended Audience :: Science/Research
Classifier: Natural Language :: English
Classifier: Programming Language :: Python :: 3.7
Classifier: Topic :: Artistic Software
Classifier: Topic :: Multimedia
Classifier: Topic :: Multimedia :: Sound/Audio
Classifier: Topic :: Multimedia :: Sound/Audio :: Editors
Classifier: Topic :: Software Development :: Libraries
License-File: LICENSE.md
Requires-Dist: torch
Requires-Dist: torchaudio
Requires-Dist: numpy
Requires-Dist: librosa
Provides-Extra: tests
Requires-Dist: pytest ; extra == 'tests'
Requires-Dist: pytest-cov ; extra == 'tests'
